CHANGELOG.md
LICENSE.txt
MANIFEST.in
README.md
setup.py
python_vagrant.egg-info/PKG-INFO
python_vagrant.egg-info/SOURCES.txt
python_vagrant.egg-info/dependency_links.txt
python_vagrant.egg-info/top_level.txt
tests/__init__.py
tests/test_vagrant.py
tests/test_vagrant_test_case.py
tests/vagrantfiles/multivm_Vagrantfile
tests/vagrantfiles/shell_provision_Vagrantfile
tests/vagrantfiles/vm_Vagrantfile
tests/vagrantfiles/multi_box/Vagrantfile
tests/vagrantfiles/single_box/Vagrantfile
vagrant/__init__.py
vagrant/compat.py
vagrant/test.py