Metadata-Version: 1.1
Name: python-vagrant
Version: 0.5.10
Summary: Python bindings for interacting with Vagrant virtual machines.
Home-page: https://github.com/todddeluca/python-vagrant
Author: Todd Francis DeLuca
Author-email: todddeluca@yahoo.com
License: MIT
Keywords: python virtual machine box vagrant virtualbox vagrantfile
Platform: UNKNOWN
Classifier: License :: OSI Approved :: MIT License
Classifier: Development Status :: 4 - Beta
Classifier: Programming Language :: Python :: 2
Classifier: Programming Language :: Python :: 2.7
Classifier: Programming Language :: Python :: 3.3
Classifier: Programming Language :: Python :: 3.4
